README.rst
setup.py
./HCCeval.py
./HCCeval_fastANI.py
./__init__.py
./getDistance.py
./pHierCC.py
./pHierCC_fastANI.py
./pHierCC_minHash.py
HierCC.egg-info/PKG-INFO
HierCC.egg-info/SOURCES.txt
HierCC.egg-info/dependency_links.txt
HierCC.egg-info/entry_points.txt
HierCC.egg-info/requires.txt
HierCC.egg-info/top_level.txt