Metadata-Version: 2.1
Name: HierCC
Version: 1.24
Summary: Hierarchical Clustering of cgMLST profiles
Home-page: https://github.com/zheminzhou/pHierCC
Author: Zhemin Zhou
Author-email: zhemin.zhou@warwick.ac.uk
License: UNKNOWN
Keywords: bioinformatics,microbial,genomics,MLST,hierarhical clustering
Platform: UNKNOWN
Classifier: Development Status :: 5 - Production/Stable
Classifier: Programming Language :: Python :: 3.6
Classifier: Programming Language :: Python :: 3.7
Classifier: Programming Language :: Python :: 3.8
Classifier: License :: OSI Approved :: GNU General Public License v3 (GPLv3)
Classifier: Operating System :: OS Independent
